CONTRIBUTING.md
LICENSE.gpl3.md
MANIFEST.in
MaTiSSe.py
README.md
setup.py
MaTiSSe.py.egg-info/PKG-INFO
MaTiSSe.py.egg-info/SOURCES.txt
MaTiSSe.py.egg-info/dependency_links.txt
MaTiSSe.py.egg-info/entry_points.txt
MaTiSSe.py.egg-info/requires.txt
MaTiSSe.py.egg-info/top_level.txt
matisse/__init__.py
matisse/__main__.py
matisse/config.py
matisse/matisse.py
matisse/data/__init__.py
matisse/data/data.py
matisse/presentation/__init__.py
matisse/presentation/metadata.py
matisse/presentation/presentation.py
matisse/presentation/regexs.py
matisse/presentation/section.py
matisse/presentation/slide.py
matisse/presentation/subsection.py
matisse/presentation/titlepage.py
matisse/presentation/toc.py
matisse/theme/__init__.py
matisse/theme/box.py
matisse/theme/canvas.py
matisse/theme/columns.py
matisse/theme/figure.py
matisse/theme/heading.py
matisse/theme/note.py
matisse/theme/selector.py
matisse/theme/table.py
matisse/theme/theme.py
matisse/theme/theme_element.py
matisse/theme/toc.py
matisse/theme/css/themes/default-skeleton.css
matisse/theme/slide/__init__.py
matisse/theme/slide/content.py
matisse/theme/slide/footer.py
matisse/theme/slide/header.py
matisse/theme/slide/position.py
matisse/theme/slide/sidebar.py
matisse/theme/slide/slide.py
matisse/utils/__init__.py
matisse/utils/mdx_mathjax.py
matisse/utils/source_editor.py
matisse/utils/utils.py
matisse/utils/css/normalize.css
matisse/utils/js/countDown.js
matisse/utils/js/MathJax/MathJax.js
matisse/utils/js/MathJax/extensions/FontWarnings.js
matisse/utils/js/MathJax/extensions/HelpDialog.js
matisse/utils/js/MathJax/extensions/MatchWebFonts.js
matisse/utils/js/MathJax/extensions/MathEvents.js
matisse/utils/js/MathJax/extensions/MathMenu.js
matisse/utils/js/MathJax/extensions/MathZoom.js
matisse/utils/js/MathJax/extensions/Safe.js
matisse/utils/js/MathJax/extensions/asciimath2jax.js
matisse/utils/js/MathJax/extensions/jsMath2jax.js
matisse/utils/js/MathJax/extensions/mml2jax.js
matisse/utils/js/MathJax/extensions/tex2jax.js
matisse/utils/js/MathJax/extensions/toMathML.js
matisse/utils/js/MathJax/extensions/HTML-CSS/handle-floats.js
matisse/utils/js/MathJax/extensions/MathML/content-mathml.js
